simple_pip_push/__init__.py
simple_upload-1.1.0.dist-info/METADATA
simple_upload-1.1.0.dist-info/WHEEL
simple_upload-1.1.0.dist-info/entry_points.txt
simple_upload-1.1.0.dist-info/top_level.txt
simple_upload-1.1.0.dist-info/RECORD
