Metadata-Version: 2.1
Name: simple-upload
Version: 1.1.0
Summary: A script to re-build and upload your package without having to remember the exact commands
Home-page: https://gitlab.com/0100001001000010/simple-upload
Author: Bruce Blore
Author-email: bruceblore@protonmail.com
License: UNKNOWN
Platform: UNKNOWN
Classifier: Programming Language :: Python :: 3
Classifier: License :: OSI Approved :: MIT License
Classifier: Operating System :: OS Independent
